magic_server/__init__.py
magic_server/main.py
magic_server-0.4.0.dist-info/entry_points.txt
magic_server-0.4.0.dist-info/WHEEL
magic_server-0.4.0.dist-info/METADATA
magic_server-0.4.0.dist-info/RECORD
